{
  "initial_capital": 1000000,
  "current_capital": 1019795.1,
  "open_positions": [],
  "closed_trades": [
    {
      "trade_id": "MEA-0001",
      "signal_type": "PUT",
      "entry_price": 96.75,
      "entry_time": "2026-02-11T13:42:46.720333",
      "quantity": 65,
      "stop_loss": 67.725,
      "target": 145.125,
      "strategy": "Mean Reversion",
      "notes": "Overbought reversal - RSI: 70.0, near resistance",
      "strike": 25950,
      "option_type": "PE",
      "spot_price": 25967.0,
      "order_action": "BUY",
      "exit_price": 113.6,
      "exit_time": "2026-02-11T14:00:17.176695",
      "status": "MANUAL_EXIT",
      "pnl": 1095.2499999999995,
      "current_price": 113.6,
      "initial_stop_loss": 67.725,
      "target_points": 0,
      "trailing_sl_stage": "INITIAL"
    },
    {
      "trade_id": "MEA-0002",
      "signal_type": "PUT",
      "entry_price": 101.85,
      "entry_time": "2026-02-11T15:00:28.332076",
      "quantity": 65,
      "stop_loss": 71.29499999999999,
      "target": 152.77499999999998,
      "strategy": "Mean Reversion",
      "notes": "Overbought reversal - RSI: 70.8, near resistance",
      "strike": 25950,
      "option_type": "PE",
      "spot_price": 25967.849609375,
      "order_action": "BUY",
      "exit_price": 109.8,
      "exit_time": "2026-02-11T15:03:33.269037",
      "status": "MANUAL_EXIT",
      "pnl": 516.7500000000002,
      "current_price": 109.8,
      "initial_stop_loss": 71.29499999999999,
      "target_points": 0,
      "trailing_sl_stage": "INITIAL"
    },
    {
      "trade_id": "MEA-0003",
      "signal_type": "CALL",
      "entry_price": 140.45,
      "entry_time": "2026-02-12T11:34:42.116757",
      "quantity": 65,
      "stop_loss": 98.31499999999998,
      "target": 210.67499999999998,
      "strategy": "Mean Reversion",
      "notes": "Oversold bounce - RSI: 12.2, near support",
      "strike": 25800,
      "option_type": "CE",
      "spot_price": 25818.19921875,
      "order_action": "BUY",
      "exit_price": 150.8,
      "exit_time": "2026-02-12T12:34:28.105124",
      "status": "MANUAL_EXIT",
      "pnl": 672.7500000000015,
      "current_price": 150.75,
      "initial_stop_loss": 98.31499999999998,
      "target_points": 0,
      "trailing_sl_stage": "INITIAL"
    },
    {
      "trade_id": "MEA-0004",
      "signal_type": "CALL",
      "entry_price": 127.75,
      "entry_time": "2026-02-12T14:46:53.391663",
      "quantity": 65,
      "stop_loss": 122.75,
      "target": 137.75,
      "strategy": "Mean Reversion",
      "notes": "Oversold bounce - RSI: 22.4, near support",
      "strike": 25800,
      "option_type": "CE",
      "spot_price": 25784.25,
      "order_action": "BUY",
      "exit_price": 122.7,
      "exit_time": "2026-02-12T14:47:08.273577",
      "status": "STOP_LOSS",
      "pnl": -328.24999999999983,
      "current_price": 122.7,
      "initial_stop_loss": 122.75,
      "target_points": 10,
      "trailing_sl_stage": "INITIAL"
    },
    {
      "trade_id": "MEA-0005",
      "signal_type": "CALL",
      "entry_price": 124.35,
      "entry_time": "2026-02-12T14:47:14.113613",
      "quantity": 65,
      "stop_loss": 119.35,
      "target": 134.35,
      "strategy": "Mean Reversion",
      "notes": "Oversold bounce - RSI: 22.1, near support",
      "strike": 25800,
      "option_type": "CE",
      "spot_price": 25782.25,
      "order_action": "BUY",
      "exit_price": 118.85,
      "exit_time": "2026-02-12T14:47:53.001252",
      "status": "STOP_LOSS",
      "pnl": -357.5,
      "current_price": 118.85,
      "initial_stop_loss": 119.35,
      "target_points": 10,
      "trailing_sl_stage": "INITIAL"
    },
    {
      "trade_id": "MEA-0006",
      "signal_type": "CALL",
      "entry_price": 119.4,
      "entry_time": "2026-02-12T14:47:57.717411",
      "quantity": 65,
      "stop_loss": 114.4,
      "target": 129.4,
      "strategy": "Mean Reversion",
      "notes": "Oversold bounce - RSI: 22.1, near support",
      "strike": 25800,
      "option_type": "CE",
      "spot_price": 25782.25,
      "order_action": "BUY",
      "exit_price": 114.25,
      "exit_time": "2026-02-12T14:49:20.063555",
      "status": "STOP_LOSS",
      "pnl": -334.75000000000034,
      "current_price": 114.25,
      "initial_stop_loss": 114.4,
      "target_points": 10,
      "trailing_sl_stage": "INITIAL"
    },
    {
      "trade_id": "MEA-0007",
      "signal_type": "CALL",
      "entry_price": 141.2,
      "entry_time": "2026-02-12T14:49:23.286497",
      "quantity": 65,
      "stop_loss": 142.2,
      "target": 151.2,
      "strategy": "Mean Reversion",
      "notes": "Oversold bounce - RSI: 18.4, near support",
      "strike": 25750,
      "option_type": "CE",
      "spot_price": 25754.55078125,
      "order_action": "BUY",
      "exit_price": 141.8,
      "exit_time": "2026-02-12T14:53:27.068454",
      "status": "STOP_LOSS",
      "pnl": 39.00000000000148,
      "current_price": 141.8,
      "initial_stop_loss": 136.2,
      "target_points": 10,
      "trailing_sl_stage": "STAGE_50"
    },
    {
      "trade_id": "B-MEA-0008",
      "signal_type": "CALL",
      "entry_price": 126.25,
      "entry_time": "2026-02-19T11:24:39.280058",
      "quantity": 65,
      "stop_loss": 127.25,
      "target": 136.25,
      "strategy": "Mean Reversion",
      "notes": "Oversold bounce - RSI: 22.8, near support",
      "strike": 25700,
      "option_type": "CE",
      "spot_price": 25682.900390625,
      "order_action": "BUY",
      "exit_price": 127.25,
      "exit_time": "2026-02-19T11:27:36.187394",
      "status": "STOP_LOSS",
      "pnl": 65.0,
      "current_price": 127.25,
      "initial_stop_loss": 121.25,
      "target_points": 10,
      "trailing_sl_stage": "STAGE_50"
    },
    {
      "trade_id": "B-MEA-0009",
      "signal_type": "CALL",
      "entry_price": 162.45,
      "entry_time": "2026-02-19T12:12:09.606271",
      "quantity": 65,
      "stop_loss": 157.45,
      "target": 172.45,
      "strategy": "Mean Reversion",
      "notes": "Oversold bounce - RSI: 4.3, near support",
      "strike": 25600,
      "option_type": "CE",
      "spot_price": 25620.5,
      "order_action": "BUY",
      "exit_price": 156.45,
      "exit_time": "2026-02-19T12:13:57.721515",
      "status": "STOP_LOSS",
      "pnl": -390.0,
      "current_price": 156.45,
      "initial_stop_loss": 157.45,
      "target_points": 10,
      "trailing_sl_stage": "INITIAL"
    },
    {
      "trade_id": "B-MEA-0010",
      "signal_type": "CALL",
      "entry_price": 156.9,
      "entry_time": "2026-02-19T12:14:00.551495",
      "quantity": 65,
      "stop_loss": 151.9,
      "target": 166.9,
      "strategy": "Mean Reversion",
      "notes": "Oversold bounce - RSI: 3.9, near support",
      "strike": 25600,
      "option_type": "CE",
      "spot_price": 25604.599609375,
      "order_action": "BUY",
      "exit_price": 151.65,
      "exit_time": "2026-02-19T12:15:17.782506",
      "status": "STOP_LOSS",
      "pnl": -341.25,
      "current_price": 151.65,
      "initial_stop_loss": 151.9,
      "target_points": 10,
      "trailing_sl_stage": "INITIAL"
    },
    {
      "trade_id": "B-MEA-0011",
      "signal_type": "CALL",
      "entry_price": 153.75,
      "entry_time": "2026-02-19T12:15:23.033835",
      "quantity": 65,
      "stop_loss": 158.75,
      "target": 163.75,
      "strategy": "Mean Reversion",
      "notes": "Oversold bounce - RSI: 3.8, near support",
      "strike": 25600,
      "option_type": "CE",
      "spot_price": 25603.5,
      "order_action": "BUY",
      "exit_price": 163.75,
      "exit_time": "2026-02-19T12:21:22.872116",
      "status": "TARGET",
      "pnl": 650.0,
      "current_price": 163.75,
      "initial_stop_loss": 148.75,
      "target_points": 10,
      "trailing_sl_stage": "STAGE_75"
    },
    {
      "trade_id": "B-MEA-0012",
      "signal_type": "CALL",
      "entry_price": 153.0,
      "entry_time": "2026-02-19T14:45:32.553836",
      "quantity": 65,
      "stop_loss": 154.0,
      "target": 163.0,
      "strategy": "Mean Reversion",
      "notes": "Oversold bounce - RSI: 29.7, near support",
      "strike": 25500,
      "option_type": "CE",
      "spot_price": 25509.349609375,
      "order_action": "BUY",
      "exit_price": 152.4,
      "exit_time": "2026-02-19T14:46:34.446860",
      "status": "STOP_LOSS",
      "pnl": -38.99999999999963,
      "current_price": 152.4,
      "initial_stop_loss": 148.0,
      "target_points": 10,
      "trailing_sl_stage": "STAGE_50"
    },
    {
      "trade_id": "B-MEA-0013",
      "signal_type": "CALL",
      "entry_price": 153.0,
      "entry_time": "2026-02-19T14:46:38.547377",
      "quantity": 65,
      "stop_loss": 148.0,
      "target": 163.0,
      "strategy": "Mean Reversion",
      "notes": "Oversold bounce - RSI: 29.6, near support",
      "strike": 25500,
      "option_type": "CE",
      "spot_price": 25508.44921875,
      "order_action": "BUY",
      "exit_price": 147.5,
      "exit_time": "2026-02-19T14:48:26.473664",
      "status": "STOP_LOSS",
      "pnl": -357.5,
      "current_price": 147.5,
      "initial_stop_loss": 148.0,
      "target_points": 10,
      "trailing_sl_stage": "INITIAL"
    },
    {
      "trade_id": "B-MEA-0014",
      "signal_type": "CALL",
      "entry_price": 144.75,
      "entry_time": "2026-02-19T14:48:31.177494",
      "quantity": 65,
      "stop_loss": 149.75,
      "target": 154.75,
      "strategy": "Mean Reversion",
      "notes": "Oversold bounce - RSI: 28.8, near support",
      "strike": 25500,
      "option_type": "CE",
      "spot_price": 25502.5,
      "order_action": "BUY",
      "exit_price": 149.4,
      "exit_time": "2026-02-19T14:53:30.471897",
      "status": "STOP_LOSS",
      "pnl": 302.25000000000034,
      "current_price": 149.4,
      "initial_stop_loss": 139.75,
      "target_points": 10,
      "trailing_sl_stage": "STAGE_75"
    },
    {
      "trade_id": "B-MEA-0015",
      "signal_type": "CALL",
      "entry_price": 153.3,
      "entry_time": "2026-02-19T15:02:02.407505",
      "quantity": 65,
      "stop_loss": 158.3,
      "target": 163.3,
      "strategy": "Mean Reversion",
      "notes": "Oversold bounce - RSI: 29.0, near support",
      "strike": 25450,
      "option_type": "CE",
      "spot_price": 25472.599609375,
      "order_action": "BUY",
      "exit_price": 163.65,
      "exit_time": "2026-02-19T15:03:35.545471",
      "status": "TARGET",
      "pnl": 672.7499999999997,
      "current_price": 163.65,
      "initial_stop_loss": 148.3,
      "target_points": 10,
      "trailing_sl_stage": "STAGE_75"
    },
    {
      "trade_id": "B-MEA-0016",
      "signal_type": "CALL",
      "entry_price": 144.5,
      "entry_time": "2026-02-19T15:07:46.795486",
      "quantity": 65,
      "stop_loss": 149.5,
      "target": 154.5,
      "strategy": "Mean Reversion",
      "notes": "Oversold bounce - RSI: 29.8, near support",
      "strike": 25450,
      "option_type": "CE",
      "spot_price": 25461.30078125,
      "order_action": "BUY",
      "exit_price": 155.4,
      "exit_time": "2026-02-19T15:09:52.594854",
      "status": "TARGET",
      "pnl": 708.5000000000003,
      "current_price": 155.4,
      "initial_stop_loss": 139.5,
      "target_points": 10,
      "trailing_sl_stage": "STAGE_75"
    },
    {
      "trade_id": "B-MEA-0017",
      "signal_type": "CALL",
      "entry_price": 150.9,
      "entry_time": "2026-02-19T15:14:14.660302",
      "quantity": 65,
      "stop_loss": 145.9,
      "target": 160.9,
      "strategy": "Mean Reversion",
      "notes": "Oversold bounce - RSI: 29.9, near support",
      "strike": 25450,
      "option_type": "CE",
      "spot_price": 25452.25,
      "order_action": "BUY",
      "exit_price": 145.35,
      "exit_time": "2026-02-19T15:15:16.701280",
      "status": "STOP_LOSS",
      "pnl": -360.75000000000074,
      "current_price": 145.35,
      "initial_stop_loss": 145.9,
      "target_points": 10,
      "trailing_sl_stage": "INITIAL"
    },
    {
      "trade_id": "B-MEA-0018",
      "signal_type": "CALL",
      "entry_price": 145.35,
      "entry_time": "2026-02-19T15:15:19.826226",
      "quantity": 65,
      "stop_loss": 140.35,
      "target": 155.35,
      "strategy": "Mean Reversion",
      "notes": "Oversold bounce - RSI: 24.4, near support",
      "strike": 25450,
      "option_type": "CE",
      "spot_price": 25440.05078125,
      "order_action": "BUY",
      "exit_price": 139.95,
      "exit_time": "2026-02-19T15:16:26.735232",
      "status": "STOP_LOSS",
      "pnl": -351.00000000000034,
      "current_price": 139.95,
      "initial_stop_loss": 140.35,
      "target_points": 10,
      "trailing_sl_stage": "INITIAL"
    },
    {
      "trade_id": "B-MEA-0019",
      "signal_type": "CALL",
      "entry_price": 138.9,
      "entry_time": "2026-02-19T15:16:29.971345",
      "quantity": 65,
      "stop_loss": 133.9,
      "target": 148.9,
      "strategy": "Mean Reversion",
      "notes": "Oversold bounce - RSI: 23.9, near support",
      "strike": 25450,
      "option_type": "CE",
      "spot_price": 25434.849609375,
      "order_action": "BUY",
      "exit_price": 132.95,
      "exit_time": "2026-02-19T15:19:22.764204",
      "status": "STOP_LOSS",
      "pnl": -386.75000000000114,
      "current_price": 132.95,
      "initial_stop_loss": 133.9,
      "target_points": 10,
      "trailing_sl_stage": "INITIAL"
    },
    {
      "trade_id": "B-MEA-0020",
      "signal_type": "CALL",
      "entry_price": 157.7,
      "entry_time": "2026-02-19T15:19:24.395396",
      "quantity": 65,
      "stop_loss": 152.7,
      "target": 167.7,
      "strategy": "Mean Reversion",
      "notes": "Oversold bounce - RSI: 22.6, near support",
      "strike": 25400,
      "option_type": "CE",
      "spot_price": 25421.150390625,
      "order_action": "BUY",
      "exit_price": 152.35,
      "exit_time": "2026-02-19T15:27:03.083561",
      "status": "STOP_LOSS",
      "pnl": -347.74999999999966,
      "current_price": 152.35,
      "initial_stop_loss": 152.7,
      "target_points": 10,
      "trailing_sl_stage": "INITIAL"
    },
    {
      "trade_id": "B-MEA-0021",
      "signal_type": "CALL",
      "entry_price": 151.45,
      "entry_time": "2026-02-19T15:27:14.678129",
      "quantity": 65,
      "stop_loss": 156.45,
      "target": 161.45,
      "strategy": "Mean Reversion",
      "notes": "Oversold bounce - RSI: 10.8, near support",
      "strike": 25400,
      "option_type": "CE",
      "spot_price": 25393.75,
      "order_action": "BUY",
      "exit_price": 167.4,
      "exit_time": "2026-02-19T15:44:48.265797",
      "status": "TARGET",
      "pnl": 1036.7500000000011,
      "current_price": 167.4,
      "initial_stop_loss": 146.45,
      "target_points": 10,
      "trailing_sl_stage": "STAGE_75"
    }
  ],
  "trade_counter": 21
}